aturan_calendar/__init__.py
aturan_calendar/__version__.py
aturan_calendar/core.py
aturan_calendar-0.3.1.dist-info/LICENSE
aturan_calendar-0.3.1.dist-info/METADATA
aturan_calendar-0.3.1.dist-info/WHEEL
aturan_calendar-0.3.1.dist-info/top_level.txt
aturan_calendar-0.3.1.dist-info/RECORD
