Metadata-Version: 2.1
Name: aturan-calendar
Version: 0.3.1
Summary: Gregorian <-> Aturan Calendar Conversion
Home-page: https://github.com/c17r/aturan-calendar
Author: Christian Sauer
Author-email: sauerc@gmail.com
License: MIT
Platform: UNKNOWN
Classifier: License :: OSI Approved :: MIT License
Classifier: Programming Language :: Python
Classifier: Programming Language :: Python :: 2.7
Classifier: Programming Language :: Python :: 3.4
Classifier: Programming Language :: Python :: 3.5
Classifier: Programming Language :: Python :: 3.6
Classifier: Programming Language :: Python :: Implementation :: CPython
Classifier: Programming Language :: Python :: Implementation :: PyPy
Requires-Dist: arrow
